carleslibs/__init__.py
carleslibs/carleslibs_demo.py
carleslibs/datetimeutils.py
carleslibs/fileutils.py
carleslibs/hashutils.py
carleslibs/keyboardutils.py
carleslibs/menuutils.py
carleslibs/osutils.py
carleslibs/pythonutils.py
carleslibs/stringutils.py
carleslibs/subprocessutils.py
carleslibs/test.py
carleslibs/version.py
carleslibs-1.0.8.dist-info/LICENSE
carleslibs-1.0.8.dist-info/METADATA
carleslibs-1.0.8.dist-info/WHEEL
carleslibs-1.0.8.dist-info/top_level.txt
carleslibs-1.0.8.dist-info/RECORD
