Metadata-Version: 2.1
Name: carleslibs
Version: 1.0.8
Summary: Carles Mateo's base libraries to fast build projects.
Home-page: https://gitlab.com/carles.mateo/carleslibs
Author: Carles Mateo
Author-email: carles.mateo@gmail.com
Project-URL: Bug Tracker, https://gitlab.com/carles.mateo/carleslibs/issues
Classifier: Programming Language :: Python :: 3
Classifier: License :: OSI Approved :: MIT License
Classifier: Operating System :: OS Independent
Requires-Python: >=3.6
License-File: LICENSE
